__init__.py
cthunder/__init__.py
cthunder/callback/__init__.py
cthunder/cli/__init__.py
cthunder/cli/cli_helper.py
cthunder/config/__init__.py
cthunder/config/config_helper_abstract.py
cthunder/config/config_helper_python.py
cthunder/config/config_helper_yaml.py
cthunder/data/__init__.py
cthunder/data/datamodule_abstract.py
cthunder/data/dataset_abstract.py
cthunder/data/sample.py
cthunder/experiments/__init__.py
cthunder/experiments/abstract_experiment.py
cthunder/features/__init__.py
cthunder/features/postprocess_abstract.py
cthunder/features/preprocess_abstract.py
cthunder/loggers/__init__.py
cthunder/loggers/default_logger.py
cthunder/loggers/logger_abstract.py
cthunder/loggers/wandb_logger.py
cthunder/pl_model/__init__.py
cthunder/pl_model/abstract_pl_model.py
cthunder/utils/__init__.py
cthunder/utils/utils.py
cthunder-0.3.18.dist-info/METADATA
cthunder-0.3.18.dist-info/WHEEL
cthunder-0.3.18.dist-info/top_level.txt
cthunder-0.3.18.dist-info/RECORD
