Metadata-Version: 2.4
Name: cthunder
Version: 0.3.18
Summary: Source code to add layers to Pytorch Lightning for training procedures.
Requires-Python: >=3.10
Requires-Dist: hydra-core>=1.3.2
Requires-Dist: lightning>=2.3.3
Requires-Dist: loguru>=0.7.3
Requires-Dist: omegaconf>=2.3.0
Requires-Dist: torch>=2.0
